pydesktop/__init__.py
pydesktop-0.0.1.dist-info/METADATA
pydesktop-0.0.1.dist-info/WHEEL
pydesktop-0.0.1.dist-info/licenses/LICENSE
pydesktop-0.0.1.dist-info/RECORD
