Metadata-Version: 2.1
Name: pydesktop
Version: 0.0.1
Summary: Desktop Entry parser
Project-URL: Homepage, https://github.com/gndu91/example_package_gndu91
Project-URL: Bug Tracker, https://github.com/gndu91/example_package_gndu91/issues
Author-email: Nadir Ghoul <fjf55bvp@duck.com>
License-File: LICENSE
Classifier: Environment :: X11 Applications :: Gnome
Classifier: Environment :: X11 Applications :: KDE
Classifier: License :: OSI Approved :: MIT License
Classifier: Operating System :: OS Independent
Classifier: Programming Language :: Python :: 3
Requires-Python: >=3.7
